{"name":"filtrar pelo tamanho L e composição Algodão","id":"filtrar-pelo-tamanho-l-e-composição-algodão:filtrar pelo tamanho L e composição Algodão","testSteps":[{"number":1,"description":"Given estou na pagina inicial do site \"\u003curl\u003e\"","duration":5449,"startTime":1519653185453,"screenshots":[{"screenshot":"986ff659f02d8c88792e38017b541f8b9e5e12e3089102d95c8488df7171439f.png"}],"result":"SUCCESS","precondition":false,"children":[{"number":2,"description":"Open home: http://10.1.10.133:8080/br/","duration":4480,"startTime":1519653185874,"screenshots":[{"screenshot":"986ff659f02d8c88792e38017b541f8b9e5e12e3089102d95c8488df7171439f.png"}],"result":"SUCCESS","precondition":false}]},{"number":3,"description":"When clico no link \u0027Todos os produtos\u0027","duration":1626,"startTime":1519653190902,"screenshots":[{"screenshot":"1e709f807ffefef946b2664518acd37e3dfcef0b4c005bd3ef16ea0a955beecf.png"}],"result":"SUCCESS","precondition":false},{"number":4,"description":"And filtro pelo tamanho \"\u003ctam\u003e\"","duration":767,"startTime":1519653192529,"screenshots":[{"screenshot":"1e709f807ffefef946b2664518acd37e3dfcef0b4c005bd3ef16ea0a955beecf.png"}],"result":"SUCCESS","precondition":false},{"number":5,"description":"And filtro pela composicao \"\u003ccomposi\u003e\"","duration":816,"startTime":1519653193297,"screenshots":[{"screenshot":"7de57811f4ac5ac29b210e72fd3443de0216b026e36faa72563f1470760eac7b.png"},{"screenshot":"b93da33426e2bb405892e3b09fd31869b02b32418bac16cacca688922844152d.png"}],"result":"SUCCESS","precondition":false},{"number":6,"description":"And removo de \u0027Filtros ativos\u0027 \"\u003cfiltro\u003e\"","duration":5789,"startTime":1519653194113,"screenshots":[{"screenshot":"ea1b892a893f3160aba1416c515dfc87eb686e157d175da416195501e4fd33f4.png"}],"result":"SUCCESS","precondition":false},{"number":7,"description":"Then verifico se o filtro foi removido","duration":296,"startTime":1519653199902,"screenshots":[{"screenshot":"ea1b892a893f3160aba1416c515dfc87eb686e157d175da416195501e4fd33f4.png"}],"result":"PENDING","precondition":false}],"userStory":{"id":"filtrar-pelo-tamanho-l-e-composição-algodão","storyName":"filtrar pelo tamanho L e composição Algodão","path":"Ct05-FiltrarPeloTamanho_L_Estilo_Vistoso.feature","type":"feature"},"featureTag":{"name":"filtrar pelo tamanho L e composição Algodão","type":"feature"},"title":"filtrar pelo tamanho L e composição Algodão","description":"","tags":[{"name":"filtrar pelo tamanho L e composição Algodão","type":"feature"},{"name":"classic","type":"tag"}],"startTime":1519653185141,"duration":0,"projectKey":"","annotatedResult":"PENDING","dataTable":{"headers":["url","tam","composi","filtro"],"rows":[{"values":["http://10.1.10.133:8080/br/","L","Algodão","Tamanho: L"],"result":"PENDING"}],"predefinedRows":true,"dataSetDescriptors":[{"startRow":0,"rowCount":0,"name":"","description":""}]},"manual":false,"result":"PENDING"}